AIDepot/Client.py
AIDepot/Resources.py
AIDepot/__init__.py
AIDepot-0.0.1.dist-info/LICENSE
AIDepot-0.0.1.dist-info/METADATA
AIDepot-0.0.1.dist-info/WHEEL
AIDepot-0.0.1.dist-info/top_level.txt
AIDepot-0.0.1.dist-info/RECORD
